avatar_yaml/__init__.py
avatar_yaml/py.typed
avatar_yaml/yaml_utils.py
avatar_yaml/models/advice.py
avatar_yaml/models/avatar_metadata.py
avatar_yaml/models/common.py
avatar_yaml/models/config.py
avatar_yaml/models/parameters.py
avatar_yaml/models/schema.py
avatar_yaml/models/volume.py
octopize_avatar_yaml-0.1.29.dist-info/METADATA
octopize_avatar_yaml-0.1.29.dist-info/WHEEL
octopize_avatar_yaml-0.1.29.dist-info/licenses/LICENSE.txt
octopize_avatar_yaml-0.1.29.dist-info/RECORD
