Metadata-Version: 2.4
Name: octopize.avatar_yaml
Version: 0.1.29
Summary: Helper functions to work with Octopize's avatar YAML files
Author-email: Octopize <pypi-octopize@octopize.io>
License: 
License-File: LICENSE.txt
Requires-Python: >=3.12
Requires-Dist: pydantic>=2.10.6
Requires-Dist: pyyaml>=6.0.2
